Vector/Vector2d.py
Vector/Vector3d.py
Vector/Vector4d.py
Vector/VectorNd.py
Vector/__init__.py
vector_pkg_enderrayquaza-2.0.5.dist-info/LICENSE
vector_pkg_enderrayquaza-2.0.5.dist-info/METADATA
vector_pkg_enderrayquaza-2.0.5.dist-info/WHEEL
vector_pkg_enderrayquaza-2.0.5.dist-info/top_level.txt
vector_pkg_enderrayquaza-2.0.5.dist-info/RECORD
