Metadata-Version: 2.1
Name: vector-pkg-enderrayquaza
Version: 2.0.5
Summary: A package with for classes Vector (2d, 3d, 4d, Nd).
Home-page: https://github.com/EnderRayquaza/Vector
Author: EnderRayquaza
Author-email: EnderRayqaza@gmail.com
License: UNKNOWN
Project-URL: Bug Tracker, https://github.com/EnderRayquaza/Vector/issues
Platform: UNKNOWN
Classifier: Programming Language :: Python :: 3
Classifier: License :: OSI Approved :: MIT License
Classifier: Operating System :: OS Independent
Requires-Python: >=3.6
